{
	"Item":{
		  "Go-FTL:www.qr-today.com":{
				"Name":"www.qr-today.com http://localhost:16040/"
			,	"TTL": 120
			,	"RequiresPing": true
			,	"PingUrl": "http://192.168.0.157:16040/api/status"
			}
		, "local:192.168.0.182":{
				"Name":"http://192.168.0.182:80/"
			,	"TTL": 120
			,	"RequiresPing": true
			,	"PingUrl": "http://192.168.0.182:80/whatever"
			}
		, "ms:get-bot":{
				"Name":"Micro Service - Get-Bot"
			,	"TTL": 120
			}
		, "ms:qr-img-decode": {
				"Name":"Micro Service - QR-Image Decode"
			,	"TTL": 120
			}
		, "ms:chat-bot":{
				"Name":"Micro Service - Chat-Bot"
			,	"TTL": 120
			}
		, "ms:tracer2-bot":{
				"Name":"Micro Service - Tracer2-Bot"
			,	"TTL": 120
			}
	 	, "ping:alive":{
				"Name":"Check Remote Services"
			,	"TTL": 120
			}
		, "remote:206-server": {
				"Name":"www.2c-why.com, etc..."
			,	"TTL": 120
			}
		, "Go-FTL:www.go-class.com":{
				"Name":"www.go-class.com http://localhost:17040/"
			,	"TTL": 120
			,	"RequiresPing": true
			,	"PingUrl": "http://192.168.0.157:17040/api/status"
			}
		, "Go-FTL:www.redux-react-class.com":{
				"Name":"www.redux-class.com http://localhost:8088/"
			,	"TTL": 120
			,	"RequiresPing": true
			,	"PingUrl": "http://192.168.0.157:8088/api/status"
			}
		, "Federated Auth Server":{
				"Name":"Federated Auth Server http://localhost:9001/"
			,	"TTL": 120
			,	"RequiresPing": true
			,	"PingUrl": "http://192.168.0.157:9001/Status"
			}
	}
}

